slowPrint/__init__.py
gptprint-0.1.dist-info/METADATA
gptprint-0.1.dist-info/WHEEL
gptprint-0.1.dist-info/top_level.txt
gptprint-0.1.dist-info/RECORD
