Metadata-Version: 2.1
Name: gptprint
Version: 0.1
Summary: A Python library for printing text with a slow chatGPT effect
Author: Harper
Author-email: developer9765@gmail.com
